skyblock/__init__.py
skyblock/skyblock.py
skyblock/types/ServerInfo.py
skyblock-0.0.1.dist-info/LICENSE
skyblock-0.0.1.dist-info/METADATA
skyblock-0.0.1.dist-info/WHEEL
skyblock-0.0.1.dist-info/top_level.txt
skyblock-0.0.1.dist-info/RECORD
